BibleOrgSys/Bible.py
BibleOrgSys/BibleOrgSysGlobals.py
BibleOrgSys/BibleWriter.py
BibleOrgSys/UnknownBible.py
BibleOrgSys/__init__.py
BibleOrgSys/Apps/Bible2USX.py
BibleOrgSys/Apps/Bible2USX_minimal.py
BibleOrgSys/Apps/__init__.py
BibleOrgSys/DataFiles/DerivedFiles/BibleBookOrders_Tables.pickle
BibleOrgSys/DataFiles/DerivedFiles/BibleBooksCodes_Tables.pickle
BibleOrgSys/DataFiles/DerivedFiles/BibleBooksNames_Tables.pickle
BibleOrgSys/DataFiles/DerivedFiles/BibleOrganisationalSystems_Tables.pickle
BibleOrgSys/DataFiles/DerivedFiles/BiblePunctuationSystems_Tables.pickle
BibleOrgSys/DataFiles/DerivedFiles/BibleVersificationSystems_Tables.pickle
BibleOrgSys/DataFiles/DerivedFiles/USFM2Markers_Tables.pickle
BibleOrgSys/DataFiles/DerivedFiles/USFM3Markers_Tables.pickle
BibleOrgSys/DataFiles/DerivedFiles/iso_639_3_Languages_Tables.pickle
BibleOrgSys/DistributedFiles/DistributedFiles.ReadMe.txt
BibleOrgSys/DistributedFiles/GreekLexicon_Strongs_Table.1.pickle
BibleOrgSys/DistributedFiles/HebrewLexicon_Tables.1.pickle
BibleOrgSys/Formats/BCVBible.py
BibleOrgSys/Formats/CSVBible.py
BibleOrgSys/Formats/DBLBible.py
BibleOrgSys/Formats/DrupalBible.py
BibleOrgSys/Formats/ESFMBible.py
BibleOrgSys/Formats/ESFMBibleBook.py
BibleOrgSys/Formats/ESwordBible.py
BibleOrgSys/Formats/ESwordCommentary.py
BibleOrgSys/Formats/EasyWorshipBible.py
BibleOrgSys/Formats/ForgeForSwordSearcherBible.py
BibleOrgSys/Formats/GoBible.py
BibleOrgSys/Formats/HaggaiXMLBible.py
BibleOrgSys/Formats/MyBibleBible.py
BibleOrgSys/Formats/MySwordBible.py
BibleOrgSys/Formats/OSISXMLBible.py
BibleOrgSys/Formats/OpenSongXMLBible.py
BibleOrgSys/Formats/PTX7Bible.py
BibleOrgSys/Formats/PTX8Bible.py
BibleOrgSys/Formats/PalmDBBible.py
BibleOrgSys/Formats/PickledBible.py
BibleOrgSys/Formats/PierceOnlineBible.py
BibleOrgSys/Formats/SwordBible.py
BibleOrgSys/Formats/SwordModules.py
BibleOrgSys/Formats/SwordResources.py
BibleOrgSys/Formats/USFM2Bible.py
BibleOrgSys/Formats/USFM2BibleBook.py
BibleOrgSys/Formats/USFMBible.py
BibleOrgSys-0.0.20.dist-info/LICENSE
BibleOrgSys-0.0.20.dist-info/METADATA
BibleOrgSys-0.0.20.dist-info/WHEEL
BibleOrgSys-0.0.20.dist-info/entry_points.txt
BibleOrgSys-0.0.20.dist-info/top_level.txt
BibleOrgSys-0.0.20.dist-info/RECORD
