Metadata-Version: 2.1
Name: BibleOrgSys
Version: 0.0.20
Summary: Bible Organisational System — load, check, and/or export Bible files/folders
Home-page: http://Freely-Given.org/Software/BibleOrganisationalSystem/
Author: Robert Hunt
Author-email: Freely.Given.org+BOS@gmail.com
License: GPLv3
Project-URL: Source Code, https://github.com/openscriptures/BibleOrgSys/
Keywords: Bible Scripture check import export index book chapter verse USFM USX
Platform: UNKNOWN
Classifier: Development Status :: 2 - Pre-Alpha
Classifier: Intended Audience :: Developers
Classifier: Intended Audience :: Religion
Classifier: Topic :: Religion
Classifier: License :: OSI Approved :: GNU General Public License v3 (GPLv3)
Classifier: Programming Language :: Python :: 3.7
Classifier: Programming Language :: Python :: 3.8
Classifier: Operating System :: OS Independent
Requires-Python: >=3.7
